setup.py
django_site/__init__.py
django_site/example.settings.py
django_site/local_settings.py
django_site/settings.py
django_site/urls.py
django_site/wsgi.py
django_site/test/__init__.py
django_site/test/test_workflow.py
uppsell/__init__.py
uppsell/admin.py
uppsell/client.py
uppsell/exceptions.py
uppsell/models.py
uppsell/resources.py
uppsell/views.py
uppsell/workflow.py
uppsell.egg-info/PKG-INFO
uppsell.egg-info/SOURCES.txt
uppsell.egg-info/dependency_links.txt
uppsell.egg-info/top_level.txt
uppsell/api/__init__.py
uppsell/api/resources.py
uppsell/api/routes.py
uppsell/migrations/0001_initial.py
uppsell/migrations/__init__.py
uppsell/util/__init__.py
uppsell/util/json.py
uppsell/util/model_fields.py
uppsell/util/request.py
uppsell/util/responses.py