Metadata-Version: 1.1
Name: uppsell
Version: 0.1
Summary: A Flask-based e-commerce API and a django-backed admin for managing them.
Home-page: https://github.com/upptalk/uppsell
Author: Adam Hayward
Author-email: adam@happy.cat
License: MIT
Keywords: example documentation tutorial
Platform: UNKNOWN
Classifier: Development Status :: 2 - Pre-Alpha
Classifier: Environment :: Web Environment
Classifier: Framework :: Django
Classifier: Framework :: Flask
Classifier: Intended Audience :: Information Technology
Classifier: Intended Audience :: Developers
Classifier: Natural Language :: English
Classifier: Topic :: Office/Business :: Financial
Classifier: Topic :: Utilities
Classifier: License :: OSI Approved :: MIT License
